{
  "email_data": {
    "emails": [],
    "labels": [],
    "sources": [],
    "descriptions": [],
    "timestamps": []
  },
  "transaction_data": {
    "transactions": [],
    "labels": [],
    "sources": [],
    "descriptions": [],
    "timestamps": []
  },
  "daily_usage_data": {
    "activities": [],
    "labels": [],
    "sources": [],
    "descriptions": [],
    "timestamps": []
  },
  "model_metadata": {
    "email_scanner": {
      "training_samples": 4,
      "test_samples": 2,
      "train_accuracy": 1.0,
      "test_accuracy": 1.0,
      "cv_mean_accuracy": 0.5,
      "cv_std_accuracy": 0.0,
      "used_tfidf": false,
      "used_accumulated_data": false,
      "total_samples": 6,
      "trained_at": "2025-11-14T10:08:33.749721"
    }
  },
  "last_updated": "2025-11-14T10:08:33.749740"
}